gajou_api/__init__.py
gajou_api/grpc/__init__.py
gajou_api/grpc/base_interceptor.py
gajou_api/grpc/base_stub.py
gajou_api/grpc/grpc_error.py
gajou_api/http/__init__.py
gajou_api/http/base_http.py
gajou_api/http/session.py
gajou_api/http/errors/__init__.py
gajou_api/http/errors/access_error.py
gajou_api/http/errors/auth_error.py
gajou_api/http/errors/bad_request_error.py
gajou_api/http/errors/base_http_error.py
gajou_api/http/errors/not_found_error.py
gajou_api/http/errors/server_error.py
gajou_api/http/errors/unprocessable_entity_error.py
gajou_api-0.1.7.dist-info/LICENSE
gajou_api-0.1.7.dist-info/METADATA
gajou_api-0.1.7.dist-info/WHEEL
gajou_api-0.1.7.dist-info/top_level.txt
gajou_api-0.1.7.dist-info/RECORD
