Metadata-Version: 2.1
Name: gajou-api
Version: 0.1.7
Summary: Base classes and helpers to make QA autotests for API
Home-page: https://github.com/ArtyomKomarenko/gajou-api
Author: Artyom Komarenko
Author-email: artyom.komarenko@mail.ru
License: MIT License
Classifier: Programming Language :: Python :: 3
Classifier: License :: OSI Approved :: MIT License
Classifier: Operating System :: OS Independent
Requires-Python: >=3.7
License-File: LICENSE
Requires-Dist: grpcio
Requires-Dist: requests
